MANIFEST.in
README.md
requirements.txt
setup.cfg
setup.py
version.py
epitome/__init__.py
epitome/constants.py
epitome/conversion.py
epitome/dataset.py
epitome/functions.py
epitome/generators.py
epitome/metrics.py
epitome/models.py
epitome/sampling.py
epitome/viz.py
epitome.egg-info/PKG-INFO
epitome.egg-info/SOURCES.txt
epitome.egg-info/dependency_links.txt
epitome.egg-info/requires.txt
epitome.egg-info/top_level.txt
epitome/test/__init__.py
epitome/test/conversion_test.py
epitome/test/dataset_test.py
epitome/test/functions_test.py
epitome/test/generators_test.py
epitome/test/metrics_test.py
epitome/test/models_test.py