Metadata-Version: 2.1
Name: epitome
Version: 0.0.1
Summary: ML model for predicting ChIP-seq peaks in new cell types from ENCODE cell lines
Home-page: UNKNOWN
Author: Alyssa Kramer Morrow
Author-email: akmorrow@berkeley.edu
License: Apache License, Version 2.0
Project-URL: Documentation, https://readthedocs.org
Project-URL: Source, https://github.com/akmorrow13/epitome
Keywords: ENCODE ChIP-seq_peaks prediction histone transcription_factor
Platform: UNKNOWN
Classifier: Topic :: Scientific/Engineering :: Bio-Informatics
Classifier: License :: OSI Approved :: Apache Software License
Classifier: Programming Language :: Python :: 3.6
Classifier: Programming Language :: Python :: 3.7
Classifier: Programming Language :: Python :: 3.8
Classifier: Programming Language :: Python :: 3.9
Requires-Python: >=3
